optimized_lssvr/__init__.py
optimized_lssvr/_bases.py
optimized_lssvr/_common.py
optimized_lssvr/_optimized_lssvr.py
optimized_lssvr/_sensitivity.py
optimized_lssvr/_simple_lssvr.py
optimized_lssvr/_version.py
optimized_lssvr/tests/__init__.py
optimized_lssvr/tests/test_common.py
optimized_lssvr/tests/test_regressor.py
optimized_lssvr-0.0.2.dist-info/LICENSE
optimized_lssvr-0.0.2.dist-info/METADATA
optimized_lssvr-0.0.2.dist-info/WHEEL
optimized_lssvr-0.0.2.dist-info/top_level.txt
optimized_lssvr-0.0.2.dist-info/RECORD
