Metadata-Version: 2.1
Name: optimized-lssvr
Version: 0.0.2
Summary: Least Squares Support Vector Regression with optimized hyperparameters
Author-email: Nico Strasdat <nstrasdat@gmail.com>
License: MIT License
Project-URL: Homepage, https://github.com/wotzlaff/sklearn-optimized-lssvr
Requires-Python: >=3.7
License-File: LICENSE
Requires-Dist: numpy
Requires-Dist: scipy
Requires-Dist: scikit-learn
